[{"class_name": "8", "bbox": "457 548 488 601", "used": false}, {"class_name": "6", "bbox": "798 566 812 571", "used": false}, {"class_name": "5", "bbox": "952 610 994 622", "used": false}, {"class_name": "6", "bbox": "827 579 847 585", "used": false}, {"class_name": "6", "bbox": "821 563 838 571", "used": false}, {"class_name": "3", "bbox": "856 574 864 582", "used": false}, {"class_name": "3", "bbox": "879 572 884 578", "used": false}, {"class_name": "1", "bbox": "856 548 930 583", "used": false}, {"class_name": "13", "bbox": "1353 702 1381 737", "used": false}, {"class_name": "13", "bbox": "996 602 1004 614", "used": false}, {"class_name": "13", "bbox": "857 574 864 582", "used": false}, {"class_name": "13", "bbox": "772 554 775 562", "used": false}]