[{"class_name": "4", "bbox": "983 830 1152 907", "used": false}, {"class_name": "5", "bbox": "1084 665 1132 685", "used": false}, {"class_name": "10", "bbox": "1264 537 1320 626", "used": false}, {"class_name": "8", "bbox": "1137 628 1144 638", "used": false}, {"class_name": "1", "bbox": "1103 587 1142 623", "used": false}, {"class_name": "13", "bbox": "1138 629 1145 644", "used": false}, {"class_name": "2", "bbox": "830 608 1004 649", "used": false}, {"class_name": "2", "bbox": "1025 608 1092 650", "used": false}, {"class_name": "2", "bbox": "1141 612 1265 653", "used": false}, {"class_name": "13", "bbox": "1128 620 1130 631", "used": false}, {"class_name": "13", "bbox": "1140 618 1141 628", "used": false}, {"class_name": "1", "bbox": "1073 592 1103 622", "used": false}]