[{"class_name": "3", "bbox": "900 584 918 608", "used": false}, {"class_name": "3", "bbox": "731 586 753 604", "used": false}, {"class_name": "6", "bbox": "914 537 940 544", "used": false}, {"class_name": "10", "bbox": "971 470 979 483", "used": false}, {"class_name": "10", "bbox": "1028 482 1031 488", "used": false}, {"class_name": "10", "bbox": "1049 481 1053 488", "used": false}, {"class_name": "7", "bbox": "1015 536 1036 547", "used": false}, {"class_name": "1", "bbox": "1123 487 1171 522", "used": false}, {"class_name": "13", "bbox": "347 577 395 605", "used": false}, {"class_name": "13", "bbox": "618 544 635 563", "used": false}, {"class_name": "13", "bbox": "713 531 727 536", "used": false}]