[{"class_name": "3", "bbox": "1013 662 1041 688", "used": false}, {"class_name": "5", "bbox": "865 596 886 622", "used": false}, {"class_name": "4", "bbox": "863 582 882 592", "used": false}, {"class_name": "10", "bbox": "837 529 845 542", "used": false}, {"class_name": "10", "bbox": "837 542 843 549", "used": false}, {"class_name": "10", "bbox": "936 529 944 544", "used": false}, {"class_name": "13", "bbox": "911 568 922 598", "used": false}, {"class_name": "13", "bbox": "1023 580 1032 609", "used": false}, {"class_name": "13", "bbox": "923 570 940 602", "used": false}, {"class_name": "1", "bbox": "811 561 842 573", "used": false}, {"class_name": "1", "bbox": "881 561 932 571", "used": false}, {"class_name": "1", "bbox": "930 562 941 572", "used": false}]