[{"class_name": "0", "bbox": "1280 638 1381 661", "used": false}, {"class_name": "0", "bbox": "803 652 912 683", "used": false}, {"class_name": "0", "bbox": "1065 644 1136 672", "used": false}, {"class_name": "0", "bbox": "307 679 461 704", "used": false}, {"class_name": "0", "bbox": "552 661 691 692", "used": false}, {"class_name": "4", "bbox": "1100 567 1126 579", "used": false}, {"class_name": "6", "bbox": "1104 547 1118 551", "used": false}, {"class_name": "7", "bbox": "1131 567 1148 573", "used": false}, {"class_name": "9", "bbox": "1227 367 1265 426", "used": true}, {"class_name": "9", "bbox": "1222 295 1261 356", "used": false}, {"class_name": "9", "bbox": "1071 497 1080 509", "used": false}, {"class_name": "9", "bbox": "1072 478 1079 494", "used": false}, {"class_name": "8", "bbox": "839 554 853 568", "used": false}, {"class_name": "10", "bbox": "963 486 975 503", "used": false}, {"class_name": "9", "bbox": "961 456 973 480", "used": false}, {"class_name": "8", "bbox": "1236 536 1250 627", "used": false}]